pdtext/__init__.py
pdtext/cl.py
pdtext/helpers.py
pdtext/io.py
pdtext/np.py
pdtext/pdf.py
pdtext/slugify.py
pdtext/sp.py
pdtext/st.py
pdtext/tf.py
pdtext/tm.py
pdtext/tools.py
pdtext/topic_models.py
pdtext-0.2.0.dist-info/LICENSE
pdtext-0.2.0.dist-info/METADATA
pdtext-0.2.0.dist-info/WHEEL
pdtext-0.2.0.dist-info/top_level.txt
pdtext-0.2.0.dist-info/RECORD
