Metadata-Version: 2.1
Name: pdtext
Version: 0.2.0
Summary: Helper functions for working with text in pandas
Home-page: https://github.com/nealcaren/pdtext
Author: Neal Caren
Author-email: neal.caren@gmail.com
License: BSD
Keywords: pandas
Platform: UNKNOWN
